{
  "Version": "2012-10-17",
  "Statement": [
    {
      "Effect": "Allow",
      "Action": [
        "cloudformation:CreateStack",
        "cloudformation:DeleteStack",
        "cloudformation:DescribeStackEvents",
        "cloudformation:DescribeStackResources",
        "cloudformation:DescribeStacks",
        "cloudformation:GetTemplate",
        "cloudformation:ListStacks",
        "cloudformation:UpdateStack",
        "cloudformation:ValidateTemplate",
        "dynamodb:CreateTable",
        "dynamodb:DeleteItem",
        "dynamodb:DeleteTable",
        "dynamodb:DescribeTable",
        "dynamodb:GetItem",
        "dynamodb:ListTables",
        "dynamodb:ListTagsOfResource",
        "dynamodb:PutItem",
        "dynamodb:Query",
        "dynamodb:Scan",
        "dynamodb:TagResource",
        "dynamodb:UntagResource",
        "dynamodb:UpdateItem",
        "dynamodb:UpdateTable",
        "iam:AttachRolePolicy",
        "iam:CreateRole",
        "iam:DeleteRole",
        "iam:DeleteRolePolicy",
        "iam:DetachRolePolicy",
        "iam:GetRole",
        "iam:GetRolePolicy",
        "iam:ListRolePolicies",
        "iam:PassRole",
        "iam:PutRolePolicy",
        "iam:TagRole",
        "iam:UntagRole",
        "lambda:AddPermission",
        "lambda:CreateEventSourceMapping",
        "lambda:CreateFunction",
        "lambda:DeleteEventSourceMapping",
        "lambda:DeleteFunction",
        "lambda:GetFunction",
        "lambda:InvokeFunction",
        "lambda:ListEventSourceMappings",
        "lambda:ListFunctions",
        "lambda:ListTags",
        "lambda:RemovePermission",
        "lambda:TagResource",
        "lambda:UntagResource",
        "lambda:UpdateEventSourceMapping",
        "lambda:UpdateFunctionCode",
        "lambda:UpdateFunctionConfiguration",
        "logs:CreateLogGroup",
        "logs:CreateLogStream",
        "logs:DescribeLogGroups",
        "logs:DescribeLogStreams",
        "logs:PutLogEvents",
        "s3:CreateBucket",
        "s3:DeleteBucket",
        "s3:DeleteBucketPolicy",
        "s3:DeleteObject",
        "s3:GetBucketAcl",
        "s3:GetBucketLocation",
        "s3:GetBucketNotification",
        "s3:GetBucketPolicy",
        "s3:GetBucketVersioning",
        "s3:GetObject",
        "s3:GetObjectAcl",
        "s3:ListBucket",
        "s3:PutBucketAcl",
        "s3:PutBucketNotification",
        "s3:PutBucketPolicy",
        "s3:PutBucketVersioning",
        "s3:PutObject",
        "s3:PutObjectAcl"
      ],
      "Resource": [
        "*",
        "arn:aws:lambda:us-east-1:*:function:adaptive-iam-service-dev-*",
        "arn:aws:s3:::adaptive-iam-service-dev-*",
        "arn:aws:s3:::adaptive-iam-service-dev-*/*",
        "arn:aws:dynamodb:us-east-1:*:table/adaptive-iam-service-dev-*"
      ]
    }
  ]
}